myugpt/__init__.py
myugpt/__main__.py
myugpt/base.py
myugpt/cli.py
myugpt/code_env.py
myugpt/dataset.py
myugpt/gpt.py
myugpt/helper.py
myugpt/llm.py
myugpt/mcts.py
myugpt/schema.py
myugpt/settings.py
myugpt-0.2.0.dist-info/LICENSE
myugpt-0.2.0.dist-info/METADATA
myugpt-0.2.0.dist-info/WHEEL
myugpt-0.2.0.dist-info/entry_points.txt
myugpt-0.2.0.dist-info/top_level.txt
myugpt-0.2.0.dist-info/RECORD
