Metadata-Version: 2.1
Name: myugpt
Version: 0.2.0
Summary: Awesome myugpt created by Cardinal-Robo-Taxi
Home-page: https://github.com/Cardinal-Robo-Taxi/MyuGPT/
Author: Cardinal-Robo-Taxi
License-File: LICENSE
Requires-Dist: pydantic
Requires-Dist: numpy
Requires-Dist: opencv-python
Requires-Dist: opencv-contrib-python
Requires-Dist: pandas
Requires-Dist: pylint
Requires-Dist: mypy
Requires-Dist: tqdm
Requires-Dist: matplotlib
Requires-Dist: types-PyYAML
Requires-Dist: scipy
Requires-Dist: ultralytics
Requires-Dist: openai
Requires-Dist: instructor ==1.3.5
Requires-Dist: sentence-transformers
Requires-Dist: pyarrow
Requires-Dist: fastparquet
Requires-Dist: langchain-community
Requires-Dist: colorama
Provides-Extra: test
Requires-Dist: pytest ; extra == 'test'
Requires-Dist: coverage ; extra == 'test'
Requires-Dist: flake8 ; extra == 'test'
Requires-Dist: black ; extra == 'test'
Requires-Dist: isort ; extra == 'test'
Requires-Dist: pytest-cov ; extra == 'test'
Requires-Dist: mypy ; extra == 'test'
Requires-Dist: gitchangelog ; extra == 'test'
Requires-Dist: mkdocs ; extra == 'test'
Requires-Dist: lark ; extra == 'test'
